django_test_signals/__init__.py
django_test_signals/signalconnectiontestcase.py
django_test_signals-0.0.5.dist-info/LICENSE
django_test_signals-0.0.5.dist-info/METADATA
django_test_signals-0.0.5.dist-info/WHEEL
django_test_signals-0.0.5.dist-info/top_level.txt
django_test_signals-0.0.5.dist-info/RECORD
